{
  "description": "Hard root prime forms at r=6149 for the 17-form budget-<= 3 tuple",
  "generated_by": "generate_hard_root_forms.py",
  "r": 6149,
  "L": 46189,
  "form_count": 17,
  "forms": [
    {
      "k": 1,
      "d": 2520,
      "alpha": 116396280,
      "beta": 15495479,
      "content": 1,
      "tau_content": 1,
      "budget": 3
    },
    {
      "k": 2,
      "d": 1260,
      "alpha": 58198140,
      "beta": 7747739,
      "content": 2,
      "tau_content": 2,
      "budget": 2
    },
    {
      "k": 3,
      "d": 840,
      "alpha": 38798760,
      "beta": 5165159,
      "content": 3,
      "tau_content": 2,
      "budget": 2
    },
    {
      "k": 4,
      "d": 630,
      "alpha": 29099070,
      "beta": 3873869,
      "content": 4,
      "tau_content": 3,
      "budget": 2
    },
    {
      "k": 5,
      "d": 504,
      "alpha": 23279256,
      "beta": 3099095,
      "content": 5,
      "tau_content": 2,
      "budget": 3
    },
    {
      "k": 6,
      "d": 420,
      "alpha": 19399380,
      "beta": 2582579,
      "content": 6,
      "tau_content": 4,
      "budget": 2
    },
    {
      "k": 8,
      "d": 315,
      "alpha": 14549535,
      "beta": 1936934,
      "content": 8,
      "tau_content": 4,
      "budget": 2
    },
    {
      "k": 9,
      "d": 280,
      "alpha": 12932920,
      "beta": 1721719,
      "content": 9,
      "tau_content": 3,
      "budget": 3
    },
    {
      "k": 10,
      "d": 252,
      "alpha": 11639628,
      "beta": 1549547,
      "content": 10,
      "tau_content": 4,
      "budget": 3
    },
    {
      "k": 11,
      "d": 2520,
      "alpha": 116396280,
      "beta": 15495469,
      "content": 209,
      "tau_content": 4,
      "budget": 3
    },
    {
      "k": 12,
      "d": 210,
      "alpha": 9699690,
      "beta": 1291289,
      "content": 12,
      "tau_content": 6,
      "budget": 2
    },
    {
      "k": 14,
      "d": 180,
      "alpha": 8314020,
      "beta": 1106819,
      "content": 238,
      "tau_content": 8,
      "budget": 2
    },
    {
      "k": 18,
      "d": 140,
      "alpha": 6466460,
      "beta": 860859,
      "content": 18,
      "tau_content": 6,
      "budget": 3
    },
    {
      "k": 20,
      "d": 126,
      "alpha": 5819814,
      "beta": 774773,
      "content": 20,
      "tau_content": 6,
      "budget": 3
    },
    {
      "k": 24,
      "d": 105,
      "alpha": 4849845,
      "beta": 645644,
      "content": 24,
      "tau_content": 8,
      "budget": 3
    },
    {
      "k": 30,
      "d": 84,
      "alpha": 3879876,
      "beta": 516515,
      "content": 570,
      "tau_content": 16,
      "budget": 2
    },
    {
      "k": 48,
      "d": 105,
      "alpha": 4849845,
      "beta": 645643,
      "content": 408,
      "tau_content": 16,
      "budget": 3
    }
  ]
}
