{
  "description": "Hard root prime forms at r=27170 for the 15-form budget-<= 3 tuple",
  "generated_by": "generate_hard_root_forms.py",
  "r": 27170,
  "L": 46189,
  "form_count": 15,
  "forms": [
    {
      "k": 1,
      "d": 2520,
      "alpha": 116396280,
      "beta": 68468399,
      "content": 1,
      "tau_content": 1,
      "budget": 3
    },
    {
      "k": 2,
      "d": 1260,
      "alpha": 58198140,
      "beta": 34234199,
      "content": 2,
      "tau_content": 2,
      "budget": 2
    },
    {
      "k": 3,
      "d": 840,
      "alpha": 38798760,
      "beta": 22822799,
      "content": 3,
      "tau_content": 2,
      "budget": 2
    },
    {
      "k": 4,
      "d": 630,
      "alpha": 29099070,
      "beta": 17117099,
      "content": 4,
      "tau_content": 3,
      "budget": 2
    },
    {
      "k": 5,
      "d": 504,
      "alpha": 23279256,
      "beta": 13693679,
      "content": 5,
      "tau_content": 2,
      "budget": 3
    },
    {
      "k": 6,
      "d": 420,
      "alpha": 19399380,
      "beta": 11411399,
      "content": 6,
      "tau_content": 4,
      "budget": 2
    },
    {
      "k": 8,
      "d": 315,
      "alpha": 14549535,
      "beta": 8558549,
      "content": 8,
      "tau_content": 4,
      "budget": 2
    },
    {
      "k": 9,
      "d": 280,
      "alpha": 12932920,
      "beta": 7607599,
      "content": 9,
      "tau_content": 3,
      "budget": 3
    },
    {
      "k": 10,
      "d": 252,
      "alpha": 11639628,
      "beta": 6846839,
      "content": 10,
      "tau_content": 4,
      "budget": 3
    },
    {
      "k": 12,
      "d": 210,
      "alpha": 9699690,
      "beta": 5705699,
      "content": 12,
      "tau_content": 6,
      "budget": 2
    },
    {
      "k": 16,
      "d": 315,
      "alpha": 14549535,
      "beta": 8558548,
      "content": 136,
      "tau_content": 8,
      "budget": 2
    },
    {
      "k": 18,
      "d": 140,
      "alpha": 6466460,
      "beta": 3803799,
      "content": 18,
      "tau_content": 6,
      "budget": 3
    },
    {
      "k": 20,
      "d": 126,
      "alpha": 5819814,
      "beta": 3423419,
      "content": 20,
      "tau_content": 6,
      "budget": 3
    },
    {
      "k": 24,
      "d": 105,
      "alpha": 4849845,
      "beta": 2852849,
      "content": 24,
      "tau_content": 8,
      "budget": 3
    },
    {
      "k": 84,
      "d": 30,
      "alpha": 1385670,
      "beta": 815099,
      "content": 1428,
      "tau_content": 24,
      "budget": 3
    }
  ]
}
